LICENSE
README.md
setup.py
cavasspy/__init__.py
cavasspy/converters.py
cavasspy/ops.py
cavasspy/registration.py
cavasspy/window_transform.py
cavasspy.egg-info/PKG-INFO
cavasspy.egg-info/SOURCES.txt
cavasspy.egg-info/dependency_links.txt
cavasspy.egg-info/requires.txt
cavasspy.egg-info/top_level.txt