Metadata-Version: 2.1
Name: cavasspy
Version: 3.0.1
Summary: CAVASS python APIs.
Author: Dai Jian
Author-email: daijian@stumail.ysu.edu.cn
Classifier: Programming Language :: Python :: 3.11
Classifier: License :: OSI Approved :: GNU General Public License v3 (GPLv3)
Classifier: Operating System :: OS Independent
Requires-Python: ~=3.11
License-File: LICENSE
